QMarkdownWidget/QMLabel.py
QMarkdownWidget/QMView.py
QMarkdownWidget/__init__.py
qmarkdownwidget-1.2.1.dist-info/licenses/LICENSE
qmarkdownwidget-1.2.1.dist-info/METADATA
qmarkdownwidget-1.2.1.dist-info/WHEEL
qmarkdownwidget-1.2.1.dist-info/top_level.txt
qmarkdownwidget-1.2.1.dist-info/RECORD
