Metadata-Version: 2.4
Name: QMarkdownWidget
Version: 1.2.1
Summary: A Python library providing modern Markdown and LaTeX widgets for PyQt/PySide.
Author-email: KercyDing <dkx215417@gmail.com>
Project-URL: Homepage, https://github.com/KercyDing/QMarkdownWidget
Project-URL: Documentation, https://github.com/KercyDing/QMarkdownWidget#readme
Project-URL: Repository, https://github.com/KercyDing/QMarkdownWidget.git
Project-URL: Issues, https://github.com/KercyDing/QMarkdownWidget/issues
Classifier: Programming Language :: Python :: 3
Classifier: License :: OSI Approved :: MIT License
Classifier: Operating System :: OS Independent
Classifier: Topic :: Software Development :: Libraries :: Python Modules
Classifier: Topic :: Text Processing :: Markup
Requires-Python: >=3.7
License-File: LICENSE
Requires-Dist: markdown-it-py>=2.0.0
Requires-Dist: linkify-it-py>=2.0.0
Requires-Dist: qtpy>=2.0.0
Provides-Extra: pyqt6
Requires-Dist: PyQt6; extra == "pyqt6"
Requires-Dist: PyQt6-WebEngine; extra == "pyqt6"
Provides-Extra: pyside6
Requires-Dist: PySide6; extra == "pyside6"
Requires-Dist: PySide6-WebEngine; extra == "pyside6"
Dynamic: license-file
